pgqmini/__init__.py
pgqmini/pgq.py
pgqmini-0.0.6.dist-info/LICENSE
pgqmini-0.0.6.dist-info/METADATA
pgqmini-0.0.6.dist-info/WHEEL
pgqmini-0.0.6.dist-info/top_level.txt
pgqmini-0.0.6.dist-info/RECORD
